dvr_pdf/__init__.py
dvr_pdf/pdf_generator.py
dvr_pdf/util/__init__.py
dvr_pdf/util/constants.py
dvr_pdf/util/custom_paragraph.py
dvr_pdf/util/enums.py
dvr_pdf/util/typing.py
dvr_pdf/util/util.py
dvr_pdf-1.0.19.dist-info/licenses/LICENSE
dvr_pdf-1.0.19.dist-info/METADATA
dvr_pdf-1.0.19.dist-info/WHEEL
dvr_pdf-1.0.19.dist-info/top_level.txt
dvr_pdf-1.0.19.dist-info/RECORD
