Metadata-Version: 2.4
Name: dvr_pdf
Version: 1.0.19
Summary: DvRD PDF generator
Author-email: Dave van Rijn Development <develop@davevanrijn.nl>
License-Expression: MIT
Keywords: PDF,generator
Classifier: Programming Language :: Python :: 3.11
Requires-Python: >=3.11
License-File: LICENSE
Requires-Dist: pydantic>=2.11.4
Requires-Dist: reportlab==4.4.1
Dynamic: license-file
